vhd/__init__.py
vhd/_vhd.py
vhd/vhd.py
vhd-1.0.7.dist-info/METADATA
vhd-1.0.7.dist-info/WHEEL
vhd-1.0.7.dist-info/top_level.txt
vhd-1.0.7.dist-info/RECORD
