Metadata-Version: 2.2
Name: vhd
Version: 1.0.7
Summary: VHD操作库
Home-page: https://gitee.com/yangyingyun/vhd
Author: ZhongYang
Author-email: 19865697458@163.com
Classifier: Programming Language :: Python :: 3
Classifier: Operating System :: OS Independent
Dynamic: author
Dynamic: author-email
Dynamic: classifier
Dynamic: description
Dynamic: description-content-type
Dynamic: home-page
Dynamic: summary
